{
    "data" :[
       
        {
            "id" : "CISL/H0/0015",
            "firstName" : "M.Sumanth",
            "designation": "Developer",
            "company" : "Captiwate",
            "salary" : "20000"
        },
        {
            "id" : "CISL/H0/0018",
            "firstName" : "B.Sai Vishal",
            "designation": "Developer",
            "company" : "Captiwate",
            "salary" : "20000"
        },
        {
            "id" : "CISL/H0/0019",
            "firstName" : "P.Harish",
            "designation": "Front END - Developer",
            "company" : "Captiwate",
            "salary" : "20000"
        },
        {
            "id" : "CISL/H0/0020",
            "firstName" : "P.Pavan Kumar",
            "designation": "Front END - Developer",
            "company" : "Captiwate",
            "salary" : "20000"
        },
        {
            "id" : "CISL/H0/0021",
            "firstName" : "G.Siva Kumar",
            "designation": "Back End - Developer",
            "company" : "Captiwate",
            "salary" : "20000"
        },
        
              {
            "id" : "CISL/H0/0022",
            "firstName" : "C.Mahendra",
            "designation": "Developer",
            "company" : "Captiwate",
            "salary" : "20000"
        },
        {
            "id" : "CISL/H0/0017",
            "firstName" : "Surekha.M",
            "designation": "Developer",
            "company" : "Captiwate",
            "salary" : "20000"
        },
        {
            "id" : "CISL/H0/0016",
            "firstName" : "Surekha.J",
            "designation": "Developer",
            "company" : "Captiwate",
            "salary" : "20000"
        },
        {
            "id" : "CISL/H0/0016",
            "firstName" : "Surekha.J",
            "designation": "Developer",
            "company" : "Captiwate",
            "salary" : "20000"
        },
        {
            "id" : "CISL/H0/0016",
            "firstName" : "Surekha.J",
            "designation": "Developer",
            "company" : "Captiwate",
            "salary" : "20000"
        },
        {
            "id" : "CISL/H0/0030",
            "firstName" : "M.Sumanth",
            "designation": "Developer",
            "company" : "Captiwate",
            "salary" : "20000"
        },
        {
            "id" : "CISL/H0/0031",
            "firstName" : "B.Sai Vishal",
            "designation": "Developer",
            "company" : "Captiwate",
            "salary" : "20000"
        }, {
            "id" : "CISL/H0/0032",
            "firstName" : "M.Sumanth",
            "designation": "Developer",
            "company" : "Captiwate",
            "salary" : "20000"
        },
        {
            "id" : "CISL/H0/0033",
            "firstName" : "B.Sai Vishal",
            "designation": "Developer",
            "company" : "Captiwate",
            "salary" : "20000"
        },
        {
            "id" : "CISL/H0/0034",
            "firstName" : "M.Sumanth",
            "designation": "Developer",
            "company" : "Captiwate",
            "salary" : "20000"
        },
        {
            "id" : "CISL/H0/0035",
            "firstName" : "B.Sai Vishal",
            "designation": "Developer",
            "company" : "Captiwate",
            "salary" : "20000"
        },
        {
            "id" : "CISL/H0/0036",
            "firstName" : "M.Sumanth",
            "designation": "Developer",
            "company" : "Captiwate",
            "salary" : "20000"
        },
        {
            "id" : "CISL/H0/0037",
            "firstName" : "B.Sai Vishal",
            "designation": "Developer",
            "company" : "Captiwate",
            "salary" : "20000"
        },
        {
            "id" : "CISL/H0/0038",
            "firstName" : "M.Sumanth",
            "designation": "Developer",
            "company" : "Captiwate",
            "salary" : "20000"
        },
        {
            "id" : "CISL/H0/0039",
            "firstName" : "B.Sai Vishal",
            "designation": "Developer",
            "company" : "Captiwate",
            "salary" : "20000"
        }, {
            "id" : "CISL/H0/0040",
            "firstName" : "M.Sumanth",
            "designation": "Developer",
            "company" : "Captiwate",
            "salary" : "20000"
        },
        {
            "id" : "CISL/H0/0041",
            "firstName" : "B.Sai Vishal",
            "designation": "Developer",
            "company" : "Captiwate",
            "salary" : "20000"
        },
        {
            "id" : "CISL/H0/0043",
            "firstName" : "B.Sai Vishal",
            "designation": "Developer",
            "company" : "Captiwate",
            "salary" : "20000"
        }
    ]
}